odoo/addons/easy_my_coop_website_portal/README.rst
odoo/addons/easy_my_coop_website_portal/__init__.py
odoo/addons/easy_my_coop_website_portal/__manifest__.py
odoo/addons/easy_my_coop_website_portal/controllers/__init__.py
odoo/addons/easy_my_coop_website_portal/controllers/portal.py
odoo/addons/easy_my_coop_website_portal/i18n/easy_my_coop_website_portal.pot
odoo/addons/easy_my_coop_website_portal/i18n/fr.po
odoo/addons/easy_my_coop_website_portal/i18n/fr_BE.po
odoo/addons/easy_my_coop_website_portal/readme/CONTRIBUTORS.rst
odoo/addons/easy_my_coop_website_portal/readme/DESCRIPTION.rst
odoo/addons/easy_my_coop_website_portal/readme/ROADMAP.rst
odoo/addons/easy_my_coop_website_portal/static/description/index.html
odoo/addons/easy_my_coop_website_portal/views/easy_my_coop_website_portal_templates.xml
odoo12_addon_easy_my_coop_website_portal-12.0.1.0.2.dist-info/METADATA
odoo12_addon_easy_my_coop_website_portal-12.0.1.0.2.dist-info/WHEEL
odoo12_addon_easy_my_coop_website_portal-12.0.1.0.2.dist-info/top_level.txt
odoo12_addon_easy_my_coop_website_portal-12.0.1.0.2.dist-info/RECORD
